buildsign/__init__.py
buildsign/__main__.py
buildsign-0.0.0.dist-info/METADATA
buildsign-0.0.0.dist-info/WHEEL
buildsign-0.0.0.dist-info/entry_points.txt
buildsign-0.0.0.dist-info/licenses/LICENSE
buildsign-0.0.0.dist-info/RECORD
