Metadata-Version: 2.4
Name: buildsign
Version: 0.0.0
Summary: Build and sign Python binaries.
Project-URL: Changes, https://blakeNaccarato.github.io/buildsign/changelog.html
Project-URL: Docs, https://blakeNaccarato.github.io/buildsign
Project-URL: Home, https://github.com/softboiler/buildsign
Project-URL: Tracker, https://github.com/softboiler/buildsign/issues
Author-email: Blake Naccarato <blake.naccarato@gmail.com>
License: MIT License
License-File: LICENSE
Classifier: License :: OSI Approved :: MIT License
Classifier: Programming Language :: Python :: 3.12
Requires-Python: >=3.12
Requires-Dist: cappa>=0.26.3
